cicflowmeter/__init__.py
cicflowmeter/constants.py
cicflowmeter/flow.py
cicflowmeter/flow_session.py
cicflowmeter/sniffer.py
cicflowmeter/utils.py
cicflowmeter/writer.py
cicflowmeter/features/__init__.py
cicflowmeter/features/flag_count.py
cicflowmeter/features/flow_bytes.py
cicflowmeter/features/packet_count.py
cicflowmeter/features/packet_length.py
cicflowmeter/features/packet_time.py
cicflowmeter/features/response_time.py
cicflowmeter/features/context/__init__.py
cicflowmeter-0.4.1.dist-info/METADATA
cicflowmeter-0.4.1.dist-info/WHEEL
cicflowmeter-0.4.1.dist-info/entry_points.txt
cicflowmeter-0.4.1.dist-info/licenses/LICENSE
cicflowmeter-0.4.1.dist-info/RECORD
