Metadata-Version: 2.4
Name: cicflowmeter
Version: 0.4.1
Summary: CICFlowMeter Python Implementation
Author-email: Hieu Le <hieulw99@gmail.com>
License: MIT
License-File: LICENSE
Classifier: License :: OSI Approved :: MIT License
Classifier: Operating System :: OS Independent
Classifier: Programming Language :: Python :: 3
Requires-Python: >=3.12
Requires-Dist: numpy>=1.26.2
Requires-Dist: requests>=2.31.0
Requires-Dist: scapy>=2.5.0
Requires-Dist: scipy>=1.11.4
